windrunner/__init__.py
windrunner/scripts/__init__.py
windrunner-0.0.1.dist-info/LICENSE
windrunner-0.0.1.dist-info/METADATA
windrunner-0.0.1.dist-info/WHEEL
windrunner-0.0.1.dist-info/dependency_links.txt
windrunner-0.0.1.dist-info/entry_points.txt
windrunner-0.0.1.dist-info/top_level.txt
windrunner-0.0.1.dist-info/RECORD
