Metadata-Version: 2.1
Name: windrunner
Version: 0.0.1
Summary: Run like the wind
Home-page: https://github.com/foadgr/windrunner
Author: Foad Green
Author-email: foadgreen@gmail.com
License: MIT License
Platform: UNKNOWN
